Workbook

Sheet 00_Навигация
A1: ОСНОВЫ РАБОТЫ С ЭЛЕКТРОННЫМИ ТАБЛИЦАМИ
A4: Все задания в одной книге. Входные данные можно менять; формулы пересчитываются.
A7: Учебные данные выбраны самостоятельно только там, где они отсутствуют в условии. Подробные ответы, допущения и исправления неточностей сценария — в документе «Отчет.docx».
A10: Лист | B10: Содержание
A11: 01_ТекстильПром | B11: Отчёт цеха, выполнение плана и прибыль
A12: 02_Сумма_среднее | B12: Задача 1: сумма и среднее
A13: 03_Среднее_без_нулей | B13: Задача 2: среднее без нулей
A14: 04_Скидка | B14: Задача 3: скидка в магазине
A15: 05_Доступ | B15: Задача 4: доступ к контенту
A16: 06_Срок_проекта | B16: Задача 5: рабочие дни
A17: 07_Дедлайн | B17: Задача 6: рабочие дни
A18: 08_Продажи | B18: Задача 7: анализ годовых продаж
A19: 09_Себестоимость | B19: Самостоятельная 1: стоимость партии с НДС
A20: 10_Качество | B20: Самостоятельная 2: контроль качества ткани
A21: 11_Заказ_праздники | B21: Самостоятельная 3: срок заказа с праздниками
... A27: 17_В5_Показатели_цеха | B27: Вариант 5: комплексный анализ цеха

Sheet 01_ТекстильПром
A1: Отчёт ООО «ТекстильПром» за месяц | P1: ← Содержание
A2: № | B2: Наименование | C2: Ед. изм. | D2: Выпуск (план) | E2: Выпуск (факт) | F2: % выполнения | G2: Себестоимость, ₽/ед. | H2: Цена продажи, ₽/ед. | I2: Прибыль, ₽/ед. | J2: Общая прибыль, ₽
A3: 1 | B3: Платья | C3: шт. | D3: 500 | E3: 470 | F3: =E3*100/D3 -> 94 | G3: 500 | H3: 1500 | I3: =H3-G3 -> 1000 | J3: =I3*E3 -> 470000
A4: 2 | B4: Футболки | C4: шт. | D4: 300 | E4: 300 | F4: =E4*100/D4 -> 100 | G4: 250 | H4: 500 | I4: =H4-G4 -> 250 | J4: =I4*E4 -> 75000
A5: 3 | B5: Джинсы | C5: шт. | D5: 400 | E5: 460 | F5: =E5*100/D5 -> 115 | G5: 800 | H5: 1700 | I5: =H5-G5 -> 900 | J5: =I5*E5 -> 414000
A6: 4 | B6: Юбки | C6: шт. | D6: 470 | E6: 450 | F6: =E6*100/D6 -> 95.744681 | G6: 300 | H6: 600 | I6: =H6-G6 -> 300 | J6: =I6*E6 -> 135000
B7: ИТОГО | D7: =SUM(D3:D6) -> 1670 | E7: =SUM(E3:E6) -> 1680 | F7: =E7*100/D7 -> 100.5988 | J7: =SUM(J3:J6) -> 1094000
A9: Пояснения и допущения — в отчёте Word.

Sheet 02_Сумма_среднее
A1: 10 | C1: Учебные данные: числа от 10 до 100 | P1: ← Содержание
A2: 20
A3: 30 | C3: Сумма | D3: =SUM(A1:A10) -> 550
A4: 40 | C4: Среднее | D4: =AVERAGE(A1:A10) -> 55
A5: 50
A6: 60
A7: 70
A8: 80
A9: 90
A10: 100
A12: Диапазон A1:A10 сохранён как в условии. Числа выбраны самостоятельно.

Sheet 03_Среднее_без_нулей
A1: Среднее без нулей | B1: =AVERAGEIF(G1:G10,"<>0") -> 40 | G1: 10 | P1: ← Содержание
G2: 0
G3: 20
G4: 30
G5: 0
G6: 40
G7: 50
G8: 0
G9: 60
G10: 70
A12: Учебные данные G1:G10: 10; 0; 20; 30; 0; 40; 50; 0; 60; 70. Нулевые значения исключены. Если все значения нулевые, среднее не определено.

Sheet 04_Скидка
A1: Сумма покупки, ₽ | B1: 6000 | P1: ← Содержание
A2: К оплате, ₽ | B2: =IF(B1>5000,B1*0.9,B1*0.95) -> 5400
A5: Покупка, ₽ | B5: К оплате, ₽ | C5: Скидка
A6: 4000 | B6: =IF(A6>5000,A6*0.9,A6*0.95) -> 3800 | C6: =IF(A6>5000,10%,5%) -> 0.05
A7: 5000 | B7: =IF(A7>5000,A7*0.9,A7*0.95) -> 4750 | C7: =IF(A7>5000,10%,5%) -> 0.05
A8: 5001 | B8: =IF(A8>5000,A8*0.9,A8*0.95) -> 4500.9 | C8: =IF(A8>5000,10%,5%) -> 0.1
A9: 6000 | B9: =IF(A9>5000,A9*0.9,A9*0.95) -> 5400 | C9: =IF(A9>5000,10%,5%) -> 0.1

Sheet 05_Доступ
A1: Возраст | C1: 18 | P1: ← Содержание
A2: Подписка | C2: Да
A3: Результат | C3: =IF(AND(C1>=18,C2="Да"),"Доступ разрешен","Отказано") -> Доступ разрешен
A6: Возраст | B6: Подписка | C6: Результат
A7: 17 | B7: Да | C7: =IF(AND(A7>=18,B7="Да"),"Доступ разрешен","Отказано") -> Отказано
A8: 18 | B8: Да | C8: =IF(AND(A8>=18,B8="Да"),"Доступ разрешен","Отказано") -> Доступ разрешен
A9: 18 | B9: Нет | C9: =IF(AND(A9>=18,B9="Да"),"Доступ разрешен","Отказано") -> Отказано
A10: 25 | B10: Нет | C10: =IF(AND(A10>=18,B10="Да"),"Доступ разрешен","Отказано") -> Отказано

Sheet 06_Срок_проекта
A1: 45566 | B1: 10 | C1: =WORKDAY(A1,B1) -> 45580 | D1: =CHOOSE(WEEKDAY(C1,2),"понедельник","вторник","среда","четверг","пятница","суббота","воскресенье") -> вторник | P1: ← Содержание
A3: A1: дата начала | B3: B1: рабочих дней | C3: C1: окончание | D3: D1: день недели
A5: Начальный день не включается. Исключаются суббота и воскресенье; праздничные даты в этих задачах не заданы. Обе задачи используют рабочие дни, поэтому результат одинаков.

Sheet 07_Дедлайн
A1: 45566 | B1: 10 | C1: =WORKDAY(A1,B1) -> 45580 | D1: =CHOOSE(WEEKDAY(C1,2),"понедельник","вторник","среда","четверг","пятница","суббота","воскресенье") -> вторник | E1: =IF(WEEKDAY(C1,2)=5,"Пятница!","") | P1: ← Содержание
A3: A1: дата начала | B3: B1: рабочих дней | C3: C1: окончание | D3: D1: день недели
A5: Начальный день не включается. Исключаются суббота и воскресенье; праздничные даты в этих задачах не заданы. Обе задачи используют рабочие дни, поэтому результат одинаков.
A9: Тест: начало | B9: Рабочих дней | C9: Окончание | D9: Проверка
A10: 45566 | B10: 8 | C10: =WORKDAY(A10,B10) -> 45576 | D10: =IF(WEEKDAY(C10,2)=5,"Пятница!","") -> Пятница!

Sheet 08_Продажи
A1: Месяц | B1: Продажи, тыс. ₽ | P1: ← Содержание
A2: Январь | B2: 120 | D2: Средние продажи | E2: =AVERAGE(B2:B13) -> 176.25
A3: Февраль | B3: 150
A4: Март | B4: 90 | D4: Месяц максимума | E4: =INDEX(A2:A13,MATCH(MAX(B2:B13),B2:B13,0)) -> Декабрь
A5: Апрель | B5: 200
A6: Май | B6: 180 | D6: Выше среднего | E6: =COUNTIF(B2:B13,">"&AVERAGE(B2:B13)) -> 6
A7: Июнь | B7: 210
A8: Июль | B8: 95 | D8: Всего за год | E8: =SUM(B2:B13) -> 2115
A9: Август | B9: 130
A10: Сентябрь | B10: 170
A11: Октябрь | B11: 220
A12: Ноябрь | B12: 250
A13: Декабрь | B13: 300

Sheet 09_Себестоимость
A1: Показатель | B1: Значение | P1: ← Содержание
A2: Расход, м/ед. | B2: 3.5
A3: Количество, ед. | B3: 1200
A4: Цена, ₽/м | B4: 250
A5: НДС | B5: 0.2
A7: Без НДС, ₽ | B7: =B2*B3*B4 -> 1050000
A8: НДС, ₽ | B8: =B7*B5 -> 210000
A9: С НДС, ₽ | B9: =ROUND(B2*B3*B4*(1+$B$5),2) -> 1260000

Sheet 10_Качество
A1: Прочность, Н/м² | B1: Отклонение цвета, % | C1: Сегмент | D1: Результат | P1: ← Содержание
A2: 55 | B2: 4 | C2: Премиум | D2: =IF(AND(A2>=50,OR(B2<=5,C2="Массмаркет")),"Годна","Брак") -> Годна
A3: 48 | B3: 3 | C3: Массмаркет | D3: =IF(AND(A3>=50,OR(B3<=5,C3="Массмаркет")),"Годна","Брак") -> Брак
A4: 50 | B4: 5 | C4: Премиум | D4: =IF(AND(A4>=50,OR(B4<=5,C4="Массмаркет")),"Годна","Брак") -> Годна
A5: 55 | B5: 8 | C5: Массмаркет | D5: =IF(AND(A5>=50,OR(B5<=5,C5="Массмаркет")),"Годна","Брак") -> Годна
A6: 55 | B6: 8 | C6: Премиум | D6: =IF(AND(A6>=50,OR(B6<=5,C6="Массмаркет")),"Годна","Брак") -> Брак
A9: Пояснения и допущения — в отчёте Word.

Sheet 11_Заказ_праздники
A1: Дата согласования | B1: Нерабочие даты | C1: Срок, раб. дней | D1: Дата окончания | P1: ← Содержание
A2: 45818 | B2: 45820 | C2: 15 | D2: =WORKDAY.INTL(A2,C2,1,$B$2:$B$3) -> 45841
B3: 45821
A5: Пояснения и допущения — в отчёте Word.

Sheet 12_Партии_ткани
A1: Партия | B1: Факт, м | C1: План, м | D1: Брак, м | E1: Себестоимость, ₽/м | F1: План, % | G1: Брак, % | H1: Показатель по условию, ₽ | P1: ← Содержание
A2: Партия 1 | B2: 1100 | C2: 1000 | D2: 20 | E2: 250 | F2: =B2/C2 -> 1.1 | G2: =D2/B2 -> 0.018181818 | H2: =(B2-D2-C2)*E2 -> 20000
A3: Партия 2 | B3: 980 | C3: 1000 | D3: 30 | E3: 260 | F3: =B3/C3 -> 0.98 | G3: =D3/B3 -> 0.030612245 | H3: =(B3-D3-C3)*E3 -> -13000
A4: Партия 3 | B4: 1250 | C4: 1200 | D4: 25 | E4: 240 | F4: =B4/C4 -> 1.0416667 | G4: =D4/B4 -> 0.02 | H4: =(B4-D4-C4)*E4 -> 6000
A5: Партия 4 | B5: 900 | C5: 950 | D5: 45 | E5: 270 | F5: =B5/C5 -> 0.94736842 | G5: =D5/B5 -> 0.05 | H5: =(B5-D5-C5)*E5 -> -25650
A6: Партия 5 | B6: 1500 | C6: 1400 | D6: 15 | E6: 230 | F6: =B6/C6 -> 1.0714286 | G6: =D6/B6 -> 0.01 | H6: =(B6-D6-C6)*E6 -> 19550
A9: Средний брак | B9: =AVERAGE(G2:G6) -> 0.025758813
A10: Лучшая партия | B10: =INDEX(A2:A6,MATCH(MAX(H2:H6),H2:H6,0)) -> Партия 1
A11: Максимум показателя | B11: =MAX(H2:H6) -> 20000
A12: Станд. откл. (выборка) | B12: =STDEV(E2:E6) -> 15.811388
A13: Взвешенный брак | B13: =SUM(D2:D6)/SUM(B2:B6) -> 0.023560209
A15: Пояснения и допущения — в отчёте Word.

Sheet 13_В1_Рабочее_время
A1: Сотрудник | B1: Дата | C1: Начало | D1: Окончание | E1: Перерыв, ч | F1: Часы | G1: Ставка, ₽/ч | H1: Зарплата, ₽ | P1: ← Содержание
A2: Иванов | B2: 46318 | C2: 0.33333333 | D2: 0.70833333 | E2: 1 | F2: =MAX(0,MOD(D2-C2,1)*24-E2) -> 8 | G2: 350 | H2: =ROUND(F2*G2,2) -> 2800
A3: Петрова | B3: 46318 | C3: 0.375 | D3: 0.75 | E3: 1 | F3: =MAX(0,MOD(D3-C3,1)*24-E3) -> 8 | G3: 400 | H3: =ROUND(F3*G3,2) -> 3200
A4: Сидоров | B4: 46318 | C4: 0.91666667 | D4: 0.25 | E4: 0.5 | F4: =MAX(0,MOD(D4-C4,1)*24-E4) -> 7.5 | G4: 380 | H4: =ROUND(F4*G4,2) -> 2850
A5: Смирнова | B5: 46318 | C5: 0.33333333 | D5: 0.66666667 | E5: 0.5 | F5: =MAX(0,MOD(D5-C5,1)*24-E5) -> 7.5 | G5: 420 | H5: =ROUND(F5*G5,2) -> 3150
A6: Кузнецов | B6: 46318 | C6: 0.41666667 | D6: 0.79166667 | E6: 1 | F6: =MAX(0,MOD(D6-C6,1)*24-E6) -> 8 | G6: 360 | H6: =ROUND(F6*G6,2) -> 2880
A8: Всего часов | B8: =SUM(F2:F6) -> 39
A9: Фонд оплаты, ₽ | B9: =SUM(H2:H6) -> 14880
A10: Средняя оплата, ₽ | B10: =AVERAGE(H2:H6) -> 2976
A12: Пояснения и допущения — в отчёте Word.

Sheet 14_В2_Склад
A1: Сырьё | B1: Ед. изм. | C1: Начальный остаток | D1: Приход | E1: Расход | F1: Текущий остаток | G1: Минимум | H1: Статус | I1: К закупке | P1: ← Содержание
A2: Хлопок | B2: м | C2: 500 | D2: 200 | E2: 600 | F2: =C2+D2-E2 -> 100 | G2: 150 | H2: =IF(F2<=G2,"Пополнить","Достаточно") -> Пополнить | I2: =MAX(0,G2-F2) -> 50
A3: Лён | B3: м | C3: 300 | D3: 100 | E3: 200 | F3: =C3+D3-E3 -> 200 | G3: 100 | H3: =IF(F3<=G3,"Пополнить","Достаточно") -> Достаточно | I3: =MAX(0,G3-F3) -> 0
A4: Шёлк | B4: м | C4: 150 | D4: 50 | E4: 170 | F4: =C4+D4-E4 -> 30 | G4: 50 | H4: =IF(F4<=G4,"Пополнить","Достаточно") -> Пополнить | I4: =MAX(0,G4-F4) -> 20
A5: Деним | B5: м | C5: 800 | D5: 300 | E5: 700 | F5: =C5+D5-E5 -> 400 | G5: 250 | H5: =IF(F5<=G5,"Пополнить","Достаточно") -> Достаточно | I5: =MAX(0,G5-F5) -> 0
A6: Подкладка | B6: м | C6: 400 | D6: 100 | E6: 420 | F6: =C6+D6-E6 -> 80 | G6: 100 | H6: =IF(F6<=G6,"Пополнить","Достаточно") -> Пополнить | I6: =MAX(0,G6-F6) -> 20
A8: Позиции к пополнению | B8: =COUNTIF(H2:H6,"Пополнить") -> 3
A9: Закупить, м | B9: =SUM(I2:I6) -> 90
A10: Остаток всего, м | B10: =SUM(F2:F6) -> 810
A12: Пояснения и допущения — в отчёте Word.

Sheet 15_В3_Производство
A1: Продукция | B1: План, шт. | C1: Факт, шт. | D1: Брак, шт. | E1: Годный выпуск | F1: План по годному, % | G1: Брак, % | H1: Отклонение, шт. | I1: Статус | P1: ← Содержание
A2: Платья | B2: 500 | C2: 470 | D2: 10 | E2: =C2-D2 -> 460 | F2: =IFERROR(E2/B2,0) -> 0.92 | G2: =IFERROR(D2/C2,0) -> 0.021276596 | H2: =E2-B2 -> -40 | I2: =IF(F2>=1,"Выполнен","Не выполнен") -> Не выполнен
A3: Футболки | B3: 300 | C3: 300 | D3: 3 | E3: =C3-D3 -> 297 | F3: =IFERROR(E3/B3,0) -> 0.99 | G3: =IFERROR(D3/C3,0) -> 0.01 | H3: =E3-B3 -> -3 | I3: =IF(F3>=1,"Выполнен","Не выполнен") -> Не выполнен
A4: Джинсы | B4: 400 | C4: 460 | D4: 6 | E4: =C4-D4 -> 454 | F4: =IFERROR(E4/B4,0) -> 1.135 | G4: =IFERROR(D4/C4,0) -> 0.013043478 | H4: =E4-B4 -> 54 | I4: =IF(F4>=1,"Выполнен","Не выполнен") -> Выполнен
A5: Юбки | B5: 470 | C5: 450 | D5: 9 | E5: =C5-D5 -> 441 | F5: =IFERROR(E5/B5,0) -> 0.93829787 | G5: =IFERROR(D5/C5,0) -> 0.02 | H5: =E5-B5 -> -29 | I5: =IF(F5>=1,"Выполнен","Не выполнен") -> Не выполнен
A7: Годный выпуск | B7: =SUM(E2:E5) -> 1652
A8: Выполнение плана | B8: =IFERROR(SUM(E2:E5)/SUM(B2:B5),0) -> 0.98922156
A9: Общий брак | B9: =IFERROR(SUM(D2:D5)/SUM(C2:C5),0) -> 0.016666667
A11: Пояснения и допущения — в отчёте Word.

Sheet 16_В4_Доставка
A1: Маршрут | B1: В одну сторону, км | C1: Рейсов | D1: Коэфф. пути | E1: Пробег, км | F1: Норма, л/100 км | G1: Топливо, л | H1: Топливо, ₽ | I1: Прочие затраты, ₽ | J1: Всего, ₽ | L1: Цена топлива, ₽/л | M1: Прочие, ₽/км | P1: ← Содержание
A2: Склад → магазин А | B2: 20 | C2: 5 | D2: 2 | E2: =B2*C2*D2 -> 200 | F2: 10 | G2: =ROUND(E2*F2/100,2) -> 20 | H2: =ROUND(G2*$L$2,2) -> 1300 | I2: =E2*$M$2 -> 2400 | J2: =SUM(H2:I2) -> 3700 | L2: 65 | M2: 12
A3: Склад → магазин Б | B3: 35 | C3: 3 | D3: 2 | E3: =B3*C3*D3 -> 210 | F3: 11 | G3: =ROUND(E3*F3/100,2) -> 23.1 | H3: =ROUND(G3*$L$2,2) -> 1501.5 | I3: =E3*$M$2 -> 2520 | J3: =SUM(H3:I3) -> 4021.5
A4: Склад → фабрика | B4: 60 | C4: 2 | D4: 2 | E4: =B4*C4*D4 -> 240 | F4: 12 | G4: =ROUND(E4*F4/100,2) -> 28.8 | H4: =ROUND(G4*$L$2,2) -> 1872 | I4: =E4*$M$2 -> 2880 | J4: =SUM(H4:I4) -> 4752
A5: Склад → пункт выдачи | B5: 15 | C5: 6 | D5: 2 | E5: =B5*C5*D5 -> 180 | F5: 9 | G5: =ROUND(E5*F5/100,2) -> 16.2 | H5: =ROUND(G5*$L$2,2) -> 1053 | I5: =E5*$M$2 -> 2160 | J5: =SUM(H5:I5) -> 3213
A7: Пробег, км | B7: =SUM(E2:E5) -> 830
A8: Топливо, л | B8: =SUM(G2:G5) -> 88.1
A9: Перевозки, ₽ | B9: =SUM(J2:J5) -> 15686.5
A10: Средняя цена км | B10: =IFERROR(SUM(J2:J5)/SUM(E2:E5),0) -> 18.899398
A12: Пояснения и допущения — в отчёте Word.

Sheet 17_В5_Показатели_цеха
A1: Продукция | B1: План, шт. | C1: Факт, шт. | D1: Брак, шт. | E1: Годный выпуск | F1: Затраты, ₽ | G1: Выручка, ₽ | H1: Прибыль, ₽ | I1: Рентабельность | J1: План по годному, % | K1: Брак, % | L1: Статус | N1: Предел брака | P1: ← Содержание
A2: ='15_В3_Производство'!A2 -> Платья | B2: ='15_В3_Производство'!B2 -> 500 | C2: ='15_В3_Производство'!C2 -> 470 | D2: ='15_В3_Производство'!D2 -> 10 | E2: =C2-D2 -> 460 | F2: =C2*'01_ТекстильПром'!G3 -> 235000 | G2: =E2*'01_ТекстильПром'!H3 -> 690000 | H2: =G2-F2 -> 455000 | I2: =IFERROR(H2/F2,0) -> 1.9361702 | J2: =IFERROR(E2/B2,0) -> 0.92 | K2: =IFERROR(D2/C2,0) -> 0.021276596 | L2: =IF(AND(J2>=1,K2<=$N$2),"Норма","Внимание") -> Внимание | N2: 0.02
A3: ='15_В3_Производство'!A3 -> Футболки | B3: ='15_В3_Производство'!B3 -> 300 | C3: ='15_В3_Производство'!C3 -> 300 | D3: ='15_В3_Производство'!D3 -> 3 | E3: =C3-D3 -> 297 | F3: =C3*'01_ТекстильПром'!G4 -> 75000 | G3: =E3*'01_ТекстильПром'!H4 -> 148500 | H3: =G3-F3 -> 73500 | I3: =IFERROR(H3/F3,0) -> 0.98 | J3: =IFERROR(E3/B3,0) -> 0.99 | K3: =IFERROR(D3/C3,0) -> 0.01 | L3: =IF(AND(J3>=1,K3<=$N$2),"Норма","Внимание") -> Внимание
A4: ='15_В3_Производство'!A4 -> Джинсы | B4: ='15_В3_Производство'!B4 -> 400 | C4: ='15_В3_Производство'!C4 -> 460 | D4: ='15_В3_Производство'!D4 -> 6 | E4: =C4-D4 -> 454 | F4: =C4*'01_ТекстильПром'!G5 -> 368000 | G4: =E4*'01_ТекстильПром'!H5 -> 771800 | H4: =G4-F4 -> 403800 | I4: =IFERROR(H4/F4,0) -> 1.0972826 | J4: =IFERROR(E4/B4,0) -> 1.135 | K4: =IFERROR(D4/C4,0) -> 0.013043478 | L4: =IF(AND(J4>=1,K4<=$N$2),"Норма","Внимание") -> Норма
A5: ='15_В3_Производство'!A5 -> Юбки | B5: ='15_В3_Производство'!B5 -> 470 | C5: ='15_В3_Производство'!C5 -> 450 | D5: ='15_В3_Производство'!D5 -> 9 | E5: =C5-D5 -> 441 | F5: =C5*'01_ТекстильПром'!G6 -> 135000 | G5: =E5*'01_ТекстильПром'!H6 -> 264600 | H5: =G5-F5 -> 129600 | I5: =IFERROR(H5/F5,0) -> 0.96 | J5: =IFERROR(E5/B5,0) -> 0.93829787 | K5: =IFERROR(D5/C5,0) -> 0.02 | L5: =IF(AND(J5>=1,K5<=$N$2),"Норма","Внимание") -> Внимание
A8: Затраты, ₽ | B8: =SUM(F2:F5) -> 813000
A9: Выручка, ₽ | B9: =SUM(G2:G5) -> 1874900
A10: Прибыль, ₽ | B10: =SUM(H2:H5) -> 1061900
A11: Рентабельность затрат | B11: =IFERROR(SUM(H2:H5)/SUM(F2:F5),0) -> 1.3061501
A12: Выполнение плана | B12: =IFERROR(SUM(E2:E5)/SUM(B2:B5),0) -> 0.98922156
A13: Доля брака | B13: =IFERROR(SUM(D2:D5)/SUM(C2:C5),0) -> 0.016666667
A14: Позиции внимания | B14: =COUNTIF(L2:L5,"Внимание") -> 3
A16: Пояснения и допущения — в отчёте Word.
